pydvdid_m/__init__.py
pydvdid_m/crc64.py
pydvdid_m/dvdid.py
pydvdid_m/pydvdid_m.py
pydvdid_m-1.1.1.dist-info/entry_points.txt
pydvdid_m-1.1.1.dist-info/LICENSE
pydvdid_m-1.1.1.dist-info/WHEEL
pydvdid_m-1.1.1.dist-info/METADATA
pydvdid_m-1.1.1.dist-info/RECORD
