Metadata-Version: 2.1
Name: pydvdid-m
Version: 1.1.1
Summary: Pure Python implementation of the Windows API method IDvdInfo2::GetDiscID.
Home-page: https://github.com/rlaphoenix/pydvdid-m
License: GPL-3.0-only
Keywords: python,dvd,win-api
Author: rlaphoenix
Author-email: rlaphoenix@pm.me
Maintainer: rlaphoenix
Maintainer-email: rlaphoenix@pm.me
Requires-Python: >=3.7,<4.0
Classifier: Development Status :: 1 - Planning
Classifier: Environment :: Console
Classifier: Intended Audience :: Developers
Classifier: License :: OSI Approved :: GNU General Public License v3 (GPLv3)
Classifier: Natural Language :: English
Classifier: Operating System :: OS Independent
Classifier: Programming Language :: Python :: 3
Classifier: Programming Language :: Python :: 3.10
Classifier: Programming Language :: Python :: 3.7
Classifier: Programming Language :: Python :: 3.8
Classifier: Programming Language :: Python :: 3.9
Classifier: Topic :: Home Automation
Classifier: Topic :: Multimedia
Classifier: Topic :: Multimedia :: Video
Classifier: Topic :: Software Development :: Libraries :: Python Modules
Classifier: Topic :: Utilities
Provides-Extra: win_raw_dev
Requires-Dist: pycdlib (>=1.12.0,<2.0.0)
Requires-Dist: python-dateutil (>=2.8.2,<3.0.0)
Requires-Dist: pywin32 (==301); (sys_platform == "win32") and (extra == "win_raw_dev")
Project-URL: Repository, https://github.com/rlaphoenix/pydvdid-m
